inspect_tool_support/__init__.py
inspect_tool_support/__main__.py
inspect_tool_support/_cli/__init__.py
inspect_tool_support/_cli/_post_install.py
inspect_tool_support/_cli/main.py
inspect_tool_support/_cli/server.py
inspect_tool_support/_cli/test_rpc_integration.py
inspect_tool_support/_in_process_tools/__init__.py
inspect_tool_support/_in_process_tools/_text_editor/__init__.py
inspect_tool_support/_in_process_tools/_text_editor/_run.py
inspect_tool_support/_in_process_tools/_text_editor/json_rpc_methods.py
inspect_tool_support/_in_process_tools/_text_editor/text_editor.py
inspect_tool_support/_in_process_tools/_text_editor/tool_types.py
inspect_tool_support/_in_process_tools/_version/__init__.py
inspect_tool_support/_in_process_tools/_version/json_rpc_methods.py
inspect_tool_support/_remote_tools/__init__.py
inspect_tool_support/_remote_tools/_bash_session/__init__.py
inspect_tool_support/_remote_tools/_bash_session/_controller.py
inspect_tool_support/_remote_tools/_bash_session/_process.py
inspect_tool_support/_remote_tools/_bash_session/_session.py
inspect_tool_support/_remote_tools/_bash_session/json_rpc_methods.py
inspect_tool_support/_remote_tools/_bash_session/tool_types.py
inspect_tool_support/_remote_tools/_mcp/__init__.py
inspect_tool_support/_remote_tools/_mcp/json_rpc_methods.py
inspect_tool_support/_remote_tools/_mcp/mcp_server_session.py
inspect_tool_support/_remote_tools/_mcp/tool_types.py
inspect_tool_support/_remote_tools/_web_browser/README.md
inspect_tool_support/_remote_tools/_web_browser/__init__.py
inspect_tool_support/_remote_tools/_web_browser/accessibility_tree.py
inspect_tool_support/_remote_tools/_web_browser/accessibility_tree_node.py
inspect_tool_support/_remote_tools/_web_browser/constants.py
inspect_tool_support/_remote_tools/_web_browser/controller.py
inspect_tool_support/_remote_tools/_web_browser/json_rpc_methods.py
inspect_tool_support/_remote_tools/_web_browser/mock_environment.py
inspect_tool_support-1.2.0.dist-info/METADATA
inspect_tool_support-1.2.0.dist-info/WHEEL
inspect_tool_support-1.2.0.dist-info/entry_points.txt
inspect_tool_support-1.2.0.dist-info/top_level.txt
inspect_tool_support-1.2.0.dist-info/RECORD
