Metadata-Version: 2.4
Name: inspect_tool_support
Version: 1.2.0
Summary: Sandbox container tool code for inspect_ai
Author: UK AI Security Institute
License: MIT License
Project-URL: CHANGELOG, https://raw.githubusercontent.com/UKGovernmentBEIS/inspect_ai/refs/heads/feature/tool-support-fast-follow/src/inspect_tool_support/CHANGELOG.md
Classifier: Development Status :: 3 - Alpha
Classifier: Environment :: Console
Classifier: Intended Audience :: Science/Research
Classifier: Intended Audience :: Developers
Classifier: License :: OSI Approved :: MIT License
Classifier: Natural Language :: English
Classifier: Programming Language :: Python :: 3
Classifier: Topic :: Scientific/Engineering :: Artificial Intelligence
Classifier: Typing :: Typed
Classifier: Operating System :: OS Independent
Requires-Python: >=3.10
Requires-Dist: aiohttp
Requires-Dist: httpx
Requires-Dist: jsonrpcserver
Requires-Dist: mcp
Requires-Dist: packaging
Requires-Dist: pydantic
Requires-Dist: returns
Requires-Dist: semver
Requires-Dist: tenacity
Requires-Dist: playwright
Requires-Dist: psutil
Provides-Extra: dev
Requires-Dist: bump2version; extra == "dev"
Requires-Dist: ruff==0.9.6; extra == "dev"
Requires-Dist: towncrier; extra == "dev"
Requires-Dist: types-psutil; extra == "dev"
Provides-Extra: dist
Requires-Dist: twine; extra == "dist"
Requires-Dist: build; extra == "dist"
